promisepay/__init__.py
promisepay/modules.py
promisepay-1.5.dist-info/DESCRIPTION.rst
promisepay-1.5.dist-info/METADATA
promisepay-1.5.dist-info/RECORD
promisepay-1.5.dist-info/WHEEL
promisepay-1.5.dist-info/metadata.json
promisepay-1.5.dist-info/top_level.txt
