Metadata-Version: 2.0
Name: promisepay
Version: 1.5
Summary: Python SDK for PromisePay/ Assemblypayments
Home-page: https://github.com/Rekvant/promisepay-python
Author: Anish Menon
Author-email: info@rekvant.com
License: Apache2
Platform: UNKNOWN
Classifier: Development Status :: 4 - Beta
Classifier: Intended Audience :: System Administrators
Classifier: License :: OSI Approved :: Apache Software License
Classifier: Programming Language :: Python :: 2.7
Requires-Dist: requests (>=2.14)
